scam/__init__.py
scam/exceptions.py
scam/keras.py
scam/utils.py
scam_net_rewintous-0.0.1.dist-info/LICENSE
scam_net_rewintous-0.0.1.dist-info/METADATA
scam_net_rewintous-0.0.1.dist-info/NOTICE
scam_net_rewintous-0.0.1.dist-info/WHEEL
scam_net_rewintous-0.0.1.dist-info/top_level.txt
scam_net_rewintous-0.0.1.dist-info/RECORD
