Metadata-Version: 2.1
Name: scam-net-rewintous
Version: 0.0.1
Summary: Score Weighted Class Activation Mapping. A tool for convolutional neural network activation analysis
Home-page: https://github.com/andreysorokin/scam-net
Author: Andrei Sorokin
Author-email: Andrey.I.Sorokin@gmail.com
License: apache-2.0
Download-URL: https://github.com/andreysorokin/scam-net/archive/0.0.1.tar.gz
Keywords: CNN,neural,heatmap
Platform: UNKNOWN
Classifier: Development Status :: 3 - Alpha
Classifier: Intended Audience :: Developers
Classifier: Topic :: Software Development :: Build Tools
Classifier: License :: OSI Approved :: MIT License
Classifier: Programming Language :: Python :: 3
Classifier: Programming Language :: Python :: 3.5
Classifier: Programming Language :: Python :: 3.6
Classifier: Programming Language :: Python :: 3.7
Requires-Dist: keras
Requires-Dist: numpy
Requires-Dist: scikit-image
Requires-Dist: matplotlib
